byakuganvisualizer/Byakugan.py
byakuganvisualizer/ImageFilter.py
byakuganvisualizer/__init__.py
byakuganvisualizer/main.py
ByakuganVisualizer-0.2.2.dist-info/METADATA
ByakuganVisualizer-0.2.2.dist-info/WHEEL
ByakuganVisualizer-0.2.2.dist-info/entry_points.txt
ByakuganVisualizer-0.2.2.dist-info/top_level.txt
ByakuganVisualizer-0.2.2.dist-info/RECORD
