Metadata-Version: 2.1
Name: ByakuganVisualizer
Version: 0.2.2
Summary: The ByakuganVisualizer repository hosts a Python tool designed to compare images and highlight their differences. It simplifies the process of identifying disparities between images, making it ideal for tasks like testing and quality assurance. Additionally, it offers options for customization, which can be helpful for color-blind users.
Home-page: https://github.com/HokageM/ByakuganVisualizer
Author: HokageM
Author-email: m.trzaska663@gmail.com
License: MIT
Project-URL: README, https://github.com/HokageM/ByakuganVisualizer/blob/main/README.md
Platform: any
Classifier: Development Status :: 4 - Beta
Classifier: Programming Language :: Python
Requires-Dist: numpy >=1.26.4
Requires-Dist: pillow >=10.2.0
Requires-Dist: importlib-metadata ; python_version < "3.8"
Provides-Extra: testing
Requires-Dist: setuptools ; extra == 'testing'
Requires-Dist: pytest ; extra == 'testing'
Requires-Dist: pytest-cov ; extra == 'testing'
